chatora/elasticsearch_ext/__init__.py
chatora/elasticsearch_ext/_pkg_info.py
chatora/elasticsearch_ext/connection/__init__.py
chatora/elasticsearch_ext/connection/http_requests.py
chatora.elasticsearch_ext-7.0.1.dist-info/LICENSE.txt
chatora.elasticsearch_ext-7.0.1.dist-info/METADATA
chatora.elasticsearch_ext-7.0.1.dist-info/WHEEL
chatora.elasticsearch_ext-7.0.1.dist-info/top_level.txt
chatora.elasticsearch_ext-7.0.1.dist-info/zip-safe
chatora.elasticsearch_ext-7.0.1.dist-info/RECORD
